loran/__init__.py
loran/check.py
loran/cmdline.py
loran/context.py
loran/fetch.py
loran/hook.py
loran/init.py
loran/ruoyi_error.py
loran/general_logic/__init__.py
loran/general_logic/database_logic.py
loran/general_logic/excel_logic.py
loran/general_logic/databases/__init__.py
loran/general_logic/databases/mysql.py
loran/general_logic/excel/__init__.py
loran/general_logic/excel/excel_assertion.py
loran/logger/__init__.py
loran/logger/logger_interface.py
loran/logic/__init__.py
loran/logic/base_api.py
loran/logic/complex_api.py
loran/logic/login_plugin.py
loran/logic/request_data.py
loran/logic/response_data.py
loran/page/__init__.py
loran/page/ui_init.py
loran/scaffold/__init__.py
loran/scaffold/cases/__init__.py
loran/scaffold/cases/api/__init__.py
loran/scaffold/cases/api/system_management/__init__.py
loran/scaffold/cases/api/system_management/user_management/__init__.py
loran/scaffold/cases/api/system_management/user_management/test_add_user_998.py
loran/scaffold/cases/api/system_management/user_management/test_adit_person_picture.py
loran/scaffold/common/__init__.py
loran/scaffold/common/login.py
loran/scaffold/common/ruoyi_logic.py
loran/scaffold/common/basic_logic/__init__.py
loran/scaffold/common/personal_center_logic/__init__.py
loran/scaffold/common/system_management_logic/__init__.py
loran/scaffold/common/system_management_logic/role_management_logic.py
loran/scaffold/common/system_management_logic/user_management_logic/__init__.py
loran/scaffold/common/system_management_logic/user_management_logic/basic.py
loran/scaffold/common/system_management_logic/user_management_logic/sphere.py
loran/scaffold/config/__init__.py
loran/scaffold/pages/__init__.py
loran/scaffold/pages/common_page/__init__.py
loran/scaffold/pages/common_page/common_action.py
loran/scaffold/pages/common_page/confirm_popup_page.py
loran/scaffold/pages/main_page/__init__.py
loran/scaffold/pages/system_management_page/__init__.py
loran-1.0.dist-info/METADATA
loran-1.0.dist-info/WHEEL
loran-1.0.dist-info/entry_points.txt
loran-1.0.dist-info/top_level.txt
loran-1.0.dist-info/RECORD
